poetry_demo_singein/__init__.py
poetry_demo_singein-0.1.0.dist-info/WHEEL
poetry_demo_singein-0.1.0.dist-info/METADATA
poetry_demo_singein-0.1.0.dist-info/RECORD
