Metadata-Version: 2.1
Name: poetry-demo-singein
Version: 0.1.0
Summary: 
Author: Singein
Author-email: singein@outlook.com
Requires-Python: >=3.7,<4.0
Classifier: Programming Language :: Python :: 3
Classifier: Programming Language :: Python :: 3.7
Classifier: Programming Language :: Python :: 3.8
Classifier: Programming Language :: Python :: 3.9
Requires-Dist: django (>=3.1.4,<4.0.0)
Requires-Dist: pendulum (>=2.1.2,<3.0.0)
Requires-Dist: requests (>=2.25.1,<3.0.0)
